starlette_validation_uploadfile.py
starlette_validation_uploadfile-0.2.0.dist-info/LICENSE
starlette_validation_uploadfile-0.2.0.dist-info/METADATA
starlette_validation_uploadfile-0.2.0.dist-info/WHEEL
starlette_validation_uploadfile-0.2.0.dist-info/top_level.txt
starlette_validation_uploadfile-0.2.0.dist-info/RECORD
