Metadata-Version: 2.1
Name: starlette-validation-uploadfile
Version: 0.2.0
Summary: Middleware for validation upload-file in FastAPI and Starlette.
Home-page: https://github.com/terib0l/starlette-validation-uploadfile
Author: terib0l
License: MIT
Keywords: starlette fastapi middleware upload file validation
Platform: UNKNOWN
Classifier: Environment :: Web Environment
Classifier: License :: OSI Approved :: MIT License
Classifier: Programming Language :: Python :: 3
Classifier: Programming Language :: Python :: 3.6
Classifier: Programming Language :: Python :: 3.7
Classifier: Programming Language :: Python :: 3.8
Requires-Python: >=3.6
License-File: LICENSE
Requires-Dist: starlette (>=0.12.11)
